AzureDataFactoryLibrary/AzureDataFactoryLibrary.py
AzureDataFactoryLibrary/__init__.py
robotframework_adf_library-0.1.4.dist-info/METADATA
robotframework_adf_library-0.1.4.dist-info/WHEEL
robotframework_adf_library-0.1.4.dist-info/licenses/LICENSE
robotframework_adf_library-0.1.4.dist-info/RECORD
